Phosphorpy/__init__.py
Phosphorpy/config/__init__.py
Phosphorpy/config/config.py
Phosphorpy/config/match.py
Phosphorpy/config/names.py
Phosphorpy/config/survey_data.py
Phosphorpy/core/__init__.py
Phosphorpy/core/functions.py
Phosphorpy/core/structure.py
Phosphorpy/data/__init__.py
Phosphorpy/data/data.py
Phosphorpy/data/mask.py
Phosphorpy/data/sub/__init__.py
Phosphorpy/data/sub/astrometry.py
Phosphorpy/data/sub/colors.py
Phosphorpy/data/sub/coordinates.py
Phosphorpy/data/sub/flux.py
Phosphorpy/data/sub/light_curve.py
Phosphorpy/data/sub/magnitudes.py
Phosphorpy/data/sub/spectra.py
Phosphorpy/data/sub/table.py
Phosphorpy/data/sub/interactive_plotting/__init__.py
Phosphorpy/data/sub/interactive_plotting/astrometry.py
Phosphorpy/data/sub/interactive_plotting/color.py
Phosphorpy/data/sub/interactive_plotting/coordinates.py
Phosphorpy/data/sub/interactive_plotting/flux.py
Phosphorpy/data/sub/interactive_plotting/interactive_plotting.py
Phosphorpy/data/sub/interactive_plotting/light_curve.py
Phosphorpy/data/sub/interactive_plotting/mangitude.py
Phosphorpy/data/sub/interactive_plotting/spectra.py
Phosphorpy/data/sub/plots/__init__.py
Phosphorpy/data/sub/plots/astrometry.py
Phosphorpy/data/sub/plots/color.py
Phosphorpy/data/sub/plots/coordinates.py
Phosphorpy/data/sub/plots/flux.py
Phosphorpy/data/sub/plots/light_curve.py
Phosphorpy/data/sub/plots/magnitude.py
Phosphorpy/data/sub/plots/plot.py
Phosphorpy/data/sub/plots/spectra.py
Phosphorpy/data/sub/tables/__init__.py
Phosphorpy/data/sub/tables/color.py
Phosphorpy/data/sub/tables/flux.py
Phosphorpy/data/sub/tables/magnitude.py
Phosphorpy/external/__init__.py
Phosphorpy/external/css.py
Phosphorpy/external/extinction.py
Phosphorpy/external/image.py
Phosphorpy/external/lamost.py
Phosphorpy/external/panstarrs.py
Phosphorpy/external/sdss.py
Phosphorpy/external/spectra.py
Phosphorpy/external/vizier.py
Phosphorpy/external/xmatch.py
Phosphorpy/external/zwicky.py
Phosphorpy/fitting/__init__.py
Phosphorpy/fitting/fit.py
Phosphorpy-0.7.5.dist-info/LICENSE
Phosphorpy-0.7.5.dist-info/METADATA
Phosphorpy-0.7.5.dist-info/WHEEL
Phosphorpy-0.7.5.dist-info/top_level.txt
Phosphorpy-0.7.5.dist-info/RECORD
