Metadata-Version: 2.1
Name: Phosphorpy
Version: 0.7.5
Summary: 
Home-page: https://github.com/patrickRauer/Phosphorpy
Author: Patrick Rauer
Author-email: j.p.rauer@sron.nl
License: GPL
Platform: UNKNOWN
Classifier: Development Status :: 3 - Alpha
Classifier: Intended Audience :: Science/Research
Classifier: Operating System :: OS Independent
Classifier: Programming Language :: Python
Classifier: Topic :: Scientific/Engineering :: Astronomy
Requires-Python: >=3.6
Requires-Dist: hypothesis
Requires-Dist: seaborn
Requires-Dist: numpy
Requires-Dist: astropy
Requires-Dist: pandas
Requires-Dist: astroquery
Requires-Dist: numba
Requires-Dist: scikit-learn
Requires-Dist: armapy (>=0.8.5)
Requires-Dist: requests
Requires-Dist: scipy
Requires-Dist: pyarrow
